{
  "platform": "Sentinel GRC",
  "version": "1.0.0-production",
  "timestamp": "2025-08-17T13:44:02.009749",
  "capabilities": {
    "frameworks_supported": 8,
    "memory_usage_mb": 62,
    "unique_features": [
      "Framework Conflict Detection",
      "CI/CD Compliance Gates",
      "Sidecar Architecture"
    ],
    "market_opportunity": "$44B growing to $160B by 2033"
  },
  "demo_results": {
    "self_assessment_possible": true,
    "pdf_generation_ready": true,
    "conflict_detection_working": true,
    "cicd_integration_operational": true
  },
  "business_value": {
    "deployment_time": "30 days vs 6 months for competitors",
    "cost_savings": "$50-200K annually vs enterprise GRC",
    "roi": "425% over 3 years"
  }
}